slovene_normalizator/__init__.py
slovene_normalizator/configatron.py
slovene_normalizator/creator.py
slovene_normalizator/declinator.py
slovene_normalizator/main_normalization.py
slovene_normalizator/pos_tagger.py
slovene_normalizator/sentence.py
slovene_normalizator/utils.py
slovene_normalizator/utils_helpers.py
slovene_normalizator/word.py
slovene_normalizator/word_type_check.py
slovene_normalizator/super_tools/__init__.py
slovene_normalizator/super_tools/sent_split.py
slovene_normalizator/super_tools/slicer.py
slovene_normalizator/super_tools/standardize_quotes.py
slovene_normalizator/super_tools/word_tokenizer.py
slovene_normalizator/support/Sloleks_lemmas_with_forms_v2.pickle
slovene_normalizator/support/__init__.py
slovene_normalizator/support/num_generator1mio.py
slovene_normalizator/support/valenca-interres-new.pickle
slovene_normalizator/support/__pycache__/__init__.cpython-310.pyc
slovene_normalizator/support/__pycache__/num_generator1mio.cpython-310.pyc
slovene_normalizator/util/__init__.py
slovene_normalizator/util/bag_of_words.json
slovene_normalizator/util/declensions.json
slovene_normalizator/util/expressions_and_declensions.json
slovene_normalizator/util/json_reader.py
slovene_normalizator/util/__pycache__/__init__.cpython-310.pyc
slovene_normalizator/util/__pycache__/json_reader.cpython-310.pyc
slovene_normalizator/util/config/basic_config.json
slovene_normalizator/util/nltk_data/tokenizers/punkt.zip
slovene_normalizator/util/nltk_data/tokenizers/punkt/README
slovene_normalizator/util/nltk_data/tokenizers/punkt/czech.pickle
slovene_normalizator/util/nltk_data/tokenizers/punkt/danish.pickle
slovene_normalizator/util/nltk_data/tokenizers/punkt/dutch.pickle
slovene_normalizator/util/nltk_data/tokenizers/punkt/english.pickle
slovene_normalizator/util/nltk_data/tokenizers/punkt/estonian.pickle
slovene_normalizator/util/nltk_data/tokenizers/punkt/finnish.pickle
slovene_normalizator/util/nltk_data/tokenizers/punkt/french.pickle
slovene_normalizator-0.0.6.dist-info/LICENSE.md
slovene_normalizator-0.0.6.dist-info/METADATA
slovene_normalizator-0.0.6.dist-info/WHEEL
slovene_normalizator-0.0.6.dist-info/top_level.txt
slovene_normalizator-0.0.6.dist-info/RECORD
